lingoshell/__init__.py
lingoshell/basic.py
lingoshell/constants.py
lingoshell/context.py
lingoshell/errors.py
lingoshell/inter.py
lingoshell/keywords.json
lingoshell/language_keywords.json
lingoshell/lexer.py
lingoshell/nodes.py
lingoshell/parser.py
lingoshell/position.py
lingoshell/results.py
lingoshell/shell.py
lingoshell/strings_with_arrows.py
lingoshell/sync.py
lingoshell/tokens.py
lingoshell/translate.py
lingoshell/values.py
lingoshell-0.0.5.dist-info/LICENSE
lingoshell-0.0.5.dist-info/METADATA
lingoshell-0.0.5.dist-info/WHEEL
lingoshell-0.0.5.dist-info/top_level.txt
lingoshell-0.0.5.dist-info/RECORD
