Metadata-Version: 2.1
Name: lingoshell
Version: 0.0.5
Summary: The LingoScript programming language
Home-page: UNKNOWN
Author: Gav H
Author-email: hi@lingoshell.com
License: UNKNOWN
Keywords: language
Platform: UNKNOWN
Classifier: Intended Audience :: Developers
